{
  "id": "http://openinterconnect.org/iotdatamodels/schemas/oic.r.mode#",
  "$schema": "http://json-schema.org/draft-04/schema#",
  "description" : "Copyright (c) 2016 Open Interconnect Consortium, Inc. All rights reserved.",
  "title": "Mode",
  "definitions": {
    "oic.r.mode": {
      "type": "object",
      "properties": {
        "supportedModes": {
          "type": "string",
          "description": "ReadOnly, Comma separated list of possible modes the device supports."
        },
        "modes":          {
          "type": "string",
          "description": "Comma separated list of the currently active mode(s)"
        }
      }
    }
  },
  "type": "object",
  "allOf": [
    {"$ref": "../../core/schemas/oic.core-schema.json#/definitions/oic.core"},
    {"$ref": "oic.baseResource.json#/definitions/oic.r.baseresource"},
    {"$ref": "#/definitions/oic.r.mode"}
  ],
  "required": ["supportedModes", "modes"]
}
